gdb_ml/__init__.py
gdb_ml/gdb_ml.py
gdb_ml-0.1.0.dist-info/AUTHORS.rst
gdb_ml-0.1.0.dist-info/LICENSE
gdb_ml-0.1.0.dist-info/METADATA
gdb_ml-0.1.0.dist-info/WHEEL
gdb_ml-0.1.0.dist-info/top_level.txt
gdb_ml-0.1.0.dist-info/RECORD
