Metadata-Version: 2.1
Name: gdb_ml
Version: 0.1.0
Summary: GDB-ML contains all the utils for a GDB machine learning based project.
Author-email: Ye Buehler <ye.buehler@outlook.com>
Maintainer-email: Ye Buehler <ye.buehler@outlook.com>
License: MIT license
Project-URL: bugs, https://github.com/Ye-Buehler/gdb_ml/issues
Project-URL: changelog, https://github.com/Ye-Buehler/gdb_ml/blob/master/changelog.md
Project-URL: homepage, https://github.com/Ye-Buehler/gdb_ml
License-File: LICENSE
License-File: AUTHORS.rst
Provides-Extra: dev
Requires-Dist: coverage ; extra == 'dev'
Requires-Dist: mypy ; extra == 'dev'
Requires-Dist: pytest ; extra == 'dev'
Requires-Dist: ruff ; extra == 'dev'
